lm_deluge/__init__.py
lm_deluge/batches.py
lm_deluge/cache.py
lm_deluge/cli.py
lm_deluge/config.py
lm_deluge/embed.py
lm_deluge/errors.py
lm_deluge/rerank.py
lm_deluge/tracker.py
lm_deluge/usage.py
lm_deluge/warnings.py
lm_deluge/api_requests/__init__.py
lm_deluge/api_requests/anthropic.py
lm_deluge/api_requests/base.py
lm_deluge/api_requests/bedrock.py
lm_deluge/api_requests/bedrock_nova.py
lm_deluge/api_requests/chat_reasoning.py
lm_deluge/api_requests/common.py
lm_deluge/api_requests/context.py
lm_deluge/api_requests/gemini.py
lm_deluge/api_requests/mistral.py
lm_deluge/api_requests/openai.py
lm_deluge/api_requests/response.py
lm_deluge/api_requests/deprecated/bedrock.py
lm_deluge/api_requests/deprecated/cohere.py
lm_deluge/api_requests/deprecated/deepseek.py
lm_deluge/api_requests/deprecated/mistral.py
lm_deluge/api_requests/deprecated/vertex.py
lm_deluge/client/__init__.py
lm_deluge/mcp/__init__.py
lm_deluge/mcp/client.py
lm_deluge/mcp/sse.py
lm_deluge/mcp/transports.py
lm_deluge/mcp/types.py
lm_deluge/models/__init__.py
lm_deluge/models/anthropic.py
lm_deluge/models/arcee.py
lm_deluge/models/azure.py
lm_deluge/models/bedrock.py
lm_deluge/models/cerebras.py
lm_deluge/models/cohere.py
lm_deluge/models/deepseek.py
lm_deluge/models/fireworks.py
lm_deluge/models/google.py
lm_deluge/models/grok.py
lm_deluge/models/groq.py
lm_deluge/models/kimi.py
lm_deluge/models/meta.py
lm_deluge/models/minimax.py
lm_deluge/models/mistral.py
lm_deluge/models/openai.py
lm_deluge/models/openrouter.py
lm_deluge/models/together.py
lm_deluge/models/zai.py
lm_deluge/pipelines/__init__.py
lm_deluge/pipelines/classify.py
lm_deluge/pipelines/extract.py
lm_deluge/pipelines/heartbeat.py
lm_deluge/pipelines/locate.py
lm_deluge/pipelines/ocr.py
lm_deluge/pipelines/score.py
lm_deluge/pipelines/translate.py
lm_deluge/pipelines/gepa/__init__.py
lm_deluge/pipelines/gepa/core.py
lm_deluge/pipelines/gepa/optimizer.py
lm_deluge/pipelines/gepa/proposer.py
lm_deluge/pipelines/gepa/util.py
lm_deluge-0.0.103.dist-info/licenses/LICENSE
lm_deluge-0.0.103.dist-info/METADATA
lm_deluge-0.0.103.dist-info/WHEEL
lm_deluge-0.0.103.dist-info/entry_points.txt
lm_deluge-0.0.103.dist-info/top_level.txt
lm_deluge-0.0.103.dist-info/RECORD
