Metadata-Version: 2.4
Name: lm_deluge
Version: 0.0.103
Summary: Python utility for using LLM API models.
Author-email: Benjamin Anderson <ben@trytaylor.ai>
Requires-Python: >=3.10
License-File: LICENSE
Requires-Dist: python-dotenv
Requires-Dist: json5
Requires-Dist: PyYAML
Requires-Dist: aiohttp
Requires-Dist: tiktoken
Requires-Dist: xxhash
Requires-Dist: tqdm
Requires-Dist: google-auth
Requires-Dist: requests-aws4auth
Requires-Dist: pydantic
Requires-Dist: bs4
Requires-Dist: lxml
Requires-Dist: pdf2image
Requires-Dist: pillow
Requires-Dist: rich
Provides-Extra: aws
Requires-Dist: boto3>=1.28.0; extra == "aws"
Provides-Extra: docker
Requires-Dist: docker>=7.0.0; extra == "docker"
Provides-Extra: full-text-search
Requires-Dist: tantivy>=0.21.0; extra == "full-text-search"
Requires-Dist: lenlp>=0.1.0; extra == "full-text-search"
Provides-Extra: sandbox
Requires-Dist: modal>=0.64.0; extra == "sandbox"
Requires-Dist: daytona-sdk>=0.1.4; extra == "sandbox"
Requires-Dist: docker>=7.0.0; extra == "sandbox"
Provides-Extra: server
Requires-Dist: fastapi>=0.100.0; extra == "server"
Requires-Dist: uvicorn>=0.20.0; extra == "server"
Provides-Extra: dev
Requires-Dist: ty; extra == "dev"
Requires-Dist: pre-commit; extra == "dev"
Dynamic: license-file
